AUTHORS.rst
CONTRIBUTING.rst
HISTORY.rst
LICENSE
MANIFEST.in
README.rst
setup.cfg
setup.py
docs/Makefile
docs/authors.rst
docs/conf.py
docs/contributing.rst
docs/history.rst
docs/index.rst
docs/installation.rst
docs/make.bat
docs/readme.rst
docs/usage.rst
rcsh/__init__.py
rcsh/rcsh.py
rcsh.egg-info/PKG-INFO
rcsh.egg-info/SOURCES.txt
rcsh.egg-info/dependency_links.txt
rcsh.egg-info/entry_points.txt
rcsh.egg-info/not-zip-safe
rcsh.egg-info/top_level.txt
tests/__init__.py
tests/test_rcsh.py
tests/test-config/.coverage
tests/test-config/rcsh
tests/test-config/rcsh.d/testdummy.exact
tests/test-config/rcsh.d/testdummy.regex