Metadata-Version: 1.1
Name: rcsh
Version: 0.2.2
Summary: Non-interactive command whitelisted shell
Home-page: https://github.com/SafPlusPlus/rcsh
Author: Freark van der Bos
Author-email: safariman@gmail.com
License: BSD license
Keywords: rcsh
Platform: UNKNOWN
Classifier: Development Status :: 2 - Pre-Alpha
Classifier: Intended Audience :: Developers
Classifier: License :: OSI Approved :: BSD License
Classifier: Natural Language :: English
Classifier: Programming Language :: Python :: 2
Classifier: Programming Language :: Python :: 2.7
Classifier: Programming Language :: Python :: 3
Classifier: Programming Language :: Python :: 3.3
Classifier: Programming Language :: Python :: 3.4
Classifier: Programming Language :: Python :: 3.5
Classifier: Programming Language :: Python :: 3.6
